dompap/Simulation.py
dompap/__init__.py
dompap/__main__.py
dompap/integrator.py
dompap/main.py
dompap/neighbor_list.py
dompap/positions.py
dompap/potential.py
dompap/tools/__init__.py
dompap/tools/autotune.py
dompap/tools/progress_bar.py
dompap/tools/run_test_simulation.py
dompap/tools/to_lammps_dump.py
dompap-0.0.5.dist-info/METADATA
dompap-0.0.5.dist-info/WHEEL
dompap-0.0.5.dist-info/licenses/LICENSE
dompap-0.0.5.dist-info/RECORD
