Metadata-Version: 2.1
Name: dompap
Version: 0.0.5
Summary: Simulations of point-like particles in any dimension with any pair potential
Project-URL: Homepage, https://github.com/urpedersen/dompap
Project-URL: Issues, https://github.com/urpedersen/dompap/issues
Project-URL: Repository, https://github.com/urpedersen/dompap
Project-URL: Changelog, https://github.com/urpedersen/dompap/blob/master/CHANGELOG.md
Author-email: "Ulf R. Pedersen" <urp@ruc.dk>
Maintainer-email: "Ulf R. Pedersen" <urp@ruc.dk>
License-File: LICENSE
Keywords: Lennard-Jones,harmonic repulsive,molecular dynamics,particle simulation,soft sphere
Classifier: Development Status :: 3 - Alpha
Classifier: Framework :: Jupyter
Classifier: Intended Audience :: Education
Classifier: Intended Audience :: Science/Research
Classifier: License :: OSI Approved :: GNU General Public License v3 (GPLv3)
Classifier: Operating System :: OS Independent
Classifier: Programming Language :: Python :: 3
Classifier: Topic :: Scientific/Engineering
Classifier: Topic :: Scientific/Engineering :: Astronomy
Classifier: Topic :: Scientific/Engineering :: Chemistry
Classifier: Topic :: Scientific/Engineering :: Physics
Requires-Python: >=3.10
Requires-Dist: matplotlib>=3.6
Requires-Dist: numba>=0.58
Requires-Dist: numpy>=1.24
Requires-Dist: pandas>=1.5
Requires-Dist: scipy>=1.10
Requires-Dist: sympy>=1.12
Requires-Dist: toml>=0.10
